git_repo_move/__init__.py
git_repo_move/cli.py
git_repo_move/gitinfo.py
git_repo_move/keepfiles.py
git_repo_move/shellscript.py
git_repo_move-1.0.1.dist-info/entry_points.txt
git_repo_move-1.0.1.dist-info/LICENSE
git_repo_move-1.0.1.dist-info/WHEEL
git_repo_move-1.0.1.dist-info/METADATA
git_repo_move-1.0.1.dist-info/RECORD
