Metadata-Version: 2.1
Name: git-repo-move
Version: 1.0.1
Summary: Move files from one git repo to another, preserving history
License: MIT
Author: Alan Rosenthal
Author-email: 1288897+AlanRosenthal@users.noreply.github.com
Requires-Python: >=3.7,<4.0
Classifier: License :: OSI Approved :: MIT License
Classifier: Programming Language :: Python :: 3
Classifier: Programming Language :: Python :: 3.7
Classifier: Programming Language :: Python :: 3.8
Classifier: Programming Language :: Python :: 3.9
Requires-Dist: click (>=7.1.2,<8.0.0)
